README.md
json_stream_parser.py
setup.py
json_stream_parser.egg-info/PKG-INFO
json_stream_parser.egg-info/SOURCES.txt
json_stream_parser.egg-info/dependency_links.txt
json_stream_parser.egg-info/entry_points.txt
json_stream_parser.egg-info/top_level.txt