Metadata-Version: 2.1
Name: json-stream-parser
Version: 0.1.dev0
Summary: parsing a stream of json objects without loading the whole stream into memory
Home-page: https://github.com/account-login/json_stream_parser
Author: account-login
Author-email: 
License: MIT
Keywords: json stream parser lazy
Platform: UNKNOWN
Classifier: Development Status :: 3 - Alpha
Classifier: License :: OSI Approved :: MIT License
Classifier: Operating System :: OS Independent
Classifier: Programming Language :: Python :: 3 :: Only
